DMT/autodoc_template/bib.bib
DMT/autodoc_template/doc
DMT/autodoc_template/documentation.tex
DMT/autodoc_template/base/header.tex
DMT/autodoc_template/base/parameters.tex
DMT/autodoc_template/content/conclusion.tex
DMT/autodoc_template/content/deckblatt.tex
DMT/autodoc_template/content/introduction.tex
DMT/extraction/__init__.py
DMT/extraction/docu_xtraction.py
DMT/extraction/extract_dimensions.py
DMT/extraction/find_nearest.py
DMT/extraction/generate_virtual_data.py
DMT/extraction/get_poly_region.py
DMT/extraction/ixbounds.py
DMT/extraction/iynorm.py
DMT/extraction/model.py
DMT/extraction/model_diode.py
DMT/extraction/mx_step.py
DMT/extraction/mx_verify.py
DMT/extraction/q_step.py
DMT/extraction/utils.py
DMT/extraction/x_diode.py
DMT/extraction/x_res.py
DMT/extraction/x_step.py
DMT/extraction/x_verify.py
DMT/extraction/x_verify_mmc.py
DMT/extraction/x_verify_plots.py
DMT/extraction/xq_poa.py
DMT/extraction/xq_poa_bilinear_full.py
DMT/extraction/xq_poa_bilinear_full_reg.py
DMT/extraction/xq_poa_classic.py
DMT/extraction/xq_poa_only_perimeter.py
DMT/extraction/xq_poa_x.py
DMT/extraction/xstep_parameter_table.py
DMT/extraction/xtraction.py
DMT/gui/__init__.py
DMT/gui/commands.py
DMT/gui/config.py
DMT/gui/file_dialog.py
DMT/gui/main_window.py
DMT/gui/mcard_widget.py
DMT/gui/utils.py
DMT/gui/x_step_gui.py
DMT/gui/x_step_widget.py
DMT/gui/xplot.py
DMT/gui/xtraction_gui.py
DMT/gui/xtraction_tree_view.py
DMT/gui/xtraction_view.py
DMT/gui/xtraction_view_ui.py
DMT/psp/__init__.py
DMT/psp/mc_psp.py
DMT/psp/psp_data_processor.py
DMT/psp/psp_default_circuits.py
DMT/psp/x_ccg.py
DMT/psp/x_cgg.py
DMT/psp/x_gds.py
DMT/psp/x_gm.py
DMT/psp/x_ib.py
DMT/psp/x_ids_vd.py
DMT/psp/x_ids_vg.py
DMT/psp/x_ig.py
DMT/psp/x_juncap_cap.py
DMT/psp/x_juncap_current.py
DMT/psp/x_y_rs.py
DMT/psp/x_y_vt.py
DMT_extraction-1.0.0.dist-info/LICENSE
DMT_extraction-1.0.0.dist-info/METADATA
DMT_extraction-1.0.0.dist-info/WHEEL
DMT_extraction-1.0.0.dist-info/top_level.txt
DMT_extraction-1.0.0.dist-info/RECORD
